[
    {
        "id": 0,
        "name": "Angie",
        "title": "My content 1",
        "text": "so good, he has been so good my God! our God is a wonder"
    },

    {
        "id": 1,
        "name": "Robert",
        "title": "My content 1",
        "src": "http://devdactic.com/video/preview1.mp4",
        "text": "so good, he has been so good my God! our God is a wonder"
    },
    {
        "id": 2,
        "name": "Philip",
        "title": "My content 1",
        "src": "http://devdactic.com/video/preview1.mp4"
    },
    {
        "id": 3,
        "name": "Lathery",
        "title": "My content 1",
        "text": "so good, he has been so good my God! our God is a wonder"
    },
    {
        "id": 4,
        "name": "Angie",
        "title": "My content 1",
        "src": "http://devdactic.com/video/preview2.mp4",
        "text": "so good, he has been so good my God! our God is a wonder"
    },
    {
        "id": 5,
        "name": "Becky",
        "title": "My content 1",
        "src": "http://devdactic.com/video/preview1.mp4"
    },
    {
        "id": 6,
        "name": "Lorena",
        "title": "My content 1",
        "text": "so good, he has been so good my God! our God is a wonder"
    },
    {
        "id": 7,
        "name": "Angie",
        "title": "My content 1",
        "text": "so good, he has been so good my God! our God is a wonder"
    },
    {
        "id": 8,
        "name": "Lorena",
        "title": "My content 1",
        "text": "so good, he has been so good my God! our God is a wonder"
    }

]